[
  {
    "id": 12171,
    "region": "worldwide",
    "period": "live",
    "direction": "departures",
    "rank": 1,
    "airport_name": "Atlanta Hartsfield-Jackson International Airport",
    "iata": "ATL",
    "country": null,
    "disruption_index": 5.0,
    "canceled_flights": 4,
    "canceled_percent": 4.0,
    "delayed_flights": 96,
    "delayed_percent": 91.0,
    "average_delay_min": 72,
    "source_name": "Flightradar24",
    "source_url": "https://www.flightradar24.com/data/airport-disruption?continent=worldwide&indices=true&period=live&type=departures",
    "fetched_at": "2026-04-28T17:32:16.503682+00:00",
    "created_at": "2026-04-28 17:32:16",
    "extra": {
      "requested_region": "worldwide",
      "used_region": "worldwide"
    }
  },
  {
    "id": 12172,
    "region": "worldwide",
    "period": "live",
    "direction": "departures",
    "rank": 2,
    "airport_name": "Shenzhen Bao'an International Airport",
    "iata": "SZX",
    "country": null,
    "disruption_index": 4.1,
    "canceled_flights": 2,
    "canceled_percent": 12.0,
    "delayed_flights": 15,
    "delayed_percent": 88.0,
    "average_delay_min": 42,
    "source_name": "Flightradar24",
    "source_url": "https://www.flightradar24.com/data/airport-disruption?continent=worldwide&indices=true&period=live&type=departures",
    "fetched_at": "2026-04-28T17:32:16.503682+00:00",
    "created_at": "2026-04-28 17:32:16",
    "extra": {
      "requested_region": "worldwide",
      "used_region": "worldwide"
    }
  },
  {
    "id": 12173,
    "region": "worldwide",
    "period": "live",
    "direction": "departures",
    "rank": 3,
    "airport_name": "Chicago Midway International Airport",
    "iata": "MDW",
    "country": null,
    "disruption_index": 2.6,
    "canceled_flights": 0,
    "canceled_percent": 0.0,
    "delayed_flights": 13,
    "delayed_percent": 62.0,
    "average_delay_min": 31,
    "source_name": "Flightradar24",
    "source_url": "https://www.flightradar24.com/data/airport-disruption?continent=worldwide&indices=true&period=live&type=departures",
    "fetched_at": "2026-04-28T17:32:16.503682+00:00",
    "created_at": "2026-04-28 17:32:16",
    "extra": {
      "requested_region": "worldwide",
      "used_region": "worldwide"
    }
  },
  {
    "id": 12174,
    "region": "worldwide",
    "period": "live",
    "direction": "departures",
    "rank": 4,
    "airport_name": "Lucknow Chaudhary Charan Singh Airport",
    "iata": "LKO",
    "country": null,
    "disruption_index": 2.6,
    "canceled_flights": 0,
    "canceled_percent": 0.0,
    "delayed_flights": 4,
    "delayed_percent": 80.0,
    "average_delay_min": 31,
    "source_name": "Flightradar24",
    "source_url": "https://www.flightradar24.com/data/airport-disruption?continent=worldwide&indices=true&period=live&type=departures",
    "fetched_at": "2026-04-28T17:32:16.503682+00:00",
    "created_at": "2026-04-28 17:32:16",
    "extra": {
      "requested_region": "worldwide",
      "used_region": "worldwide"
    }
  },
  {
    "id": 12175,
    "region": "worldwide",
    "period": "live",
    "direction": "departures",
    "rank": 5,
    "airport_name": "Guangzhou Baiyun International Airport",
    "iata": "CAN",
    "country": null,
    "disruption_index": 2.4,
    "canceled_flights": 0,
    "canceled_percent": 0.0,
    "delayed_flights": 10,
    "delayed_percent": 77.0,
    "average_delay_min": 29,
    "source_name": "Flightradar24",
    "source_url": "https://www.flightradar24.com/data/airport-disruption?continent=worldwide&indices=true&period=live&type=departures",
    "fetched_at": "2026-04-28T17:32:16.503682+00:00",
    "created_at": "2026-04-28 17:32:16",
    "extra": {
      "requested_region": "worldwide",
      "used_region": "worldwide"
    }
  },
  {
    "id": 12176,
    "region": "worldwide",
    "period": "live",
    "direction": "departures",
    "rank": 6,
    "airport_name": "Moscow Sheremetyevo International Airport",
    "iata": "SVO",
    "country": null,
    "disruption_index": 2.4,
    "canceled_flights": 0,
    "canceled_percent": 0.0,
    "delayed_flights": 27,
    "delayed_percent": 87.0,
    "average_delay_min": 29,
    "source_name": "Flightradar24",
    "source_url": "https://www.flightradar24.com/data/airport-disruption?continent=worldwide&indices=true&period=live&type=departures",
    "fetched_at": "2026-04-28T17:32:16.503682+00:00",
    "created_at": "2026-04-28 17:32:16",
    "extra": {
      "requested_region": "worldwide",
      "used_region": "worldwide"
    }
  },
  {
    "id": 12177,
    "region": "worldwide",
    "period": "live",
    "direction": "departures",
    "rank": 7,
    "airport_name": "Moscow Vnukovo International Airport",
    "iata": "VKO",
    "country": null,
    "disruption_index": 2.4,
    "canceled_flights": 0,
    "canceled_percent": 0.0,
    "delayed_flights": 8,
    "delayed_percent": 89.0,
    "average_delay_min": 29,
    "source_name": "Flightradar24",
    "source_url": "https://www.flightradar24.com/data/airport-disruption?continent=worldwide&indices=true&period=live&type=departures",
    "fetched_at": "2026-04-28T17:32:16.503682+00:00",
    "created_at": "2026-04-28 17:32:16",
    "extra": {
      "requested_region": "worldwide",
      "used_region": "worldwide"
    }
  },
  {
    "id": 12178,
    "region": "worldwide",
    "period": "live",
    "direction": "departures",
    "rank": 8,
    "airport_name": "Chicago O'Hare International Airport",
    "iata": "ORD",
    "country": null,
    "disruption_index": 2.4,
    "canceled_flights": 2,
    "canceled_percent": 1.0,
    "delayed_flights": 106,
    "delayed_percent": 75.0,
    "average_delay_min": 28,
    "source_name": "Flightradar24",
    "source_url": "https://www.flightradar24.com/data/airport-disruption?continent=worldwide&indices=true&period=live&type=departures",
    "fetched_at": "2026-04-28T17:32:16.503682+00:00",
    "created_at": "2026-04-28 17:32:16",
    "extra": {
      "requested_region": "worldwide",
      "used_region": "worldwide"
    }
  },
  {
    "id": 12179,
    "region": "worldwide",
    "period": "live",
    "direction": "departures",
    "rank": 9,
    "airport_name": "Taipei Taoyuan International Airport",
    "iata": "TPE",
    "country": null,
    "disruption_index": 2.4,
    "canceled_flights": 0,
    "canceled_percent": 0.0,
    "delayed_flights": 20,
    "delayed_percent": 83.0,
    "average_delay_min": 29,
    "source_name": "Flightradar24",
    "source_url": "https://www.flightradar24.com/data/airport-disruption?continent=worldwide&indices=true&period=live&type=departures",
    "fetched_at": "2026-04-28T17:32:16.503682+00:00",
    "created_at": "2026-04-28 17:32:16",
    "extra": {
      "requested_region": "worldwide",
      "used_region": "worldwide"
    }
  },
  {
    "id": 12180,
    "region": "worldwide",
    "period": "live",
    "direction": "departures",
    "rank": 10,
    "airport_name": "Rome Ciampino Airport",
    "iata": "CIA",
    "country": null,
    "disruption_index": 2.1,
    "canceled_flights": 0,
    "canceled_percent": 0.0,
    "delayed_flights": 4,
    "delayed_percent": 67.0,
    "average_delay_min": 25,
    "source_name": "Flightradar24",
    "source_url": "https://www.flightradar24.com/data/airport-disruption?continent=worldwide&indices=true&period=live&type=departures",
    "fetched_at": "2026-04-28T17:32:16.503682+00:00",
    "created_at": "2026-04-28 17:32:16",
    "extra": {
      "requested_region": "worldwide",
      "used_region": "worldwide"
    }
  }
]