{
  "today_factor": 0.7428581642432591,
  "database_size": 68989,
  "updated_at": "2026-04-09T04:25:54Z",
  "fetched_at": "2026-04-09T04:26:01.877318+00:00",
  "rows": [
    {
      "rank": 1,
      "item_name": "P250 | 设施系列·草图 (崭新出厂)",
      "daily_volume": "675",
      "min_price": "0.51",
      "best_sell_ratio": "0.573",
      "best_buy_ratio": "0.586",
      "safe_buy_ratio": "0.586",
      "recent_ratio": "0.567",
      "platform": "BUFF",
      "steam_market": "Steam",
      "updated_text": "3m 40s"
    },
    {
      "rank": 2,
      "item_name": "封装的涂鸦 | 心 (丁香)",
      "daily_volume": "297",
      "min_price": "0.91",
      "best_sell_ratio": "0.595",
      "best_buy_ratio": "0.599",
      "safe_buy_ratio": "0.599",
      "recent_ratio": "0.623",
      "platform": "UUYP",
      "steam_market": "Steam",
      "updated_text": "4m 10s"
    },
    {
      "rank": 3,
      "item_name": "Sealed Dead Hand Terminal",
      "daily_volume": "117792",
      "min_price": "17.00",
      "best_sell_ratio": "0.606",
      "best_buy_ratio": "0.606",
      "safe_buy_ratio": "0.607",
      "recent_ratio": "0.685",
      "platform": "UUYP",
      "steam_market": "Steam",
      "updated_text": "6m 27s"
    },
    {
      "rank": 4,
      "item_name": "新星 | Turquoise Pour (略有磨损)",
      "daily_volume": "314",
      "min_price": "0.65",
      "best_sell_ratio": "0.537",
      "best_buy_ratio": "0.542",
      "safe_buy_ratio": "0.625",
      "recent_ratio": "0.730",
      "platform": "UUYP",
      "steam_market": "Steam",
      "updated_text": "1m 5s"
    },
    {
      "rank": 5,
      "item_name": "AK-47 | 橄榄迷彩 (略有磨损)",
      "daily_volume": "1634",
      "min_price": "0.86",
      "best_sell_ratio": "0.614",
      "best_buy_ratio": "0.628",
      "safe_buy_ratio": "0.628",
      "recent_ratio": "0.656",
      "platform": "UUYP",
      "steam_market": "Steam",
      "updated_text": "6m 12s"
    },
    {
      "rank": 6,
      "item_name": "PP-野牛 | RMX (破损不堪)",
      "daily_volume": "201",
      "min_price": "0.96",
      "best_sell_ratio": "0.398",
      "best_buy_ratio": "0.632",
      "safe_buy_ratio": "0.632",
      "recent_ratio": "0.644",
      "platform": "UUYP",
      "steam_market": "Steam",
      "updated_text": "6m 27s"
    },
    {
      "rank": 7,
      "item_name": "FN57 | 午夜喷涂 (崭新出厂)",
      "daily_volume": "477",
      "min_price": "1.81",
      "best_sell_ratio": "0.628",
      "best_buy_ratio": "0.633",
      "safe_buy_ratio": "0.633",
      "recent_ratio": "0.646",
      "platform": "UUYP",
      "steam_market": "Steam",
      "updated_text": "1m 25s"
    },
    {
      "rank": 8,
      "item_name": "裂空武器箱",
      "daily_volume": "52922",
      "min_price": "3.71",
      "best_sell_ratio": "0.627",
      "best_buy_ratio": "0.628",
      "safe_buy_ratio": "0.634",
      "recent_ratio": "0.629",
      "platform": "UUYP",
      "steam_market": "Steam",
      "updated_text": "4m 17s"
    },
    {
      "rank": 9,
      "item_name": "P90 | 擦擦 (崭新出厂)",
      "daily_volume": "641",
      "min_price": "1.82",
      "best_sell_ratio": "0.615",
      "best_buy_ratio": "0.636",
      "safe_buy_ratio": "0.636",
      "recent_ratio": "0.632",
      "platform": "UUYP",
      "steam_market": "Steam",
      "updated_text": "5m 41s"
    },
    {
      "rank": 10,
      "item_name": "MP5-SD | 霓虹榨汁机 (久经沙场)",
      "daily_volume": "1852",
      "min_price": "0.74",
      "best_sell_ratio": "0.617",
      "best_buy_ratio": "0.638",
      "safe_buy_ratio": "0.638",
      "recent_ratio": "0.655",
      "platform": "UUYP",
      "steam_market": "Steam",
      "updated_text": "1m 32s"
    }
  ]
}