[
  {
    "key": "nasdaq",
    "name": "NASDAQ Composite",
    "symbol": "^IXIC",
    "price": 22902.895,
    "change_percent": 0.35,
    "source": "yahoo_finance",
    "fetched_at": "2026-04-12T03:25:18.444601+00:00"
  },
  {
    "key": "sp500",
    "name": "S&P 500",
    "symbol": "^GSPC",
    "price": 6816.89,
    "change_percent": -0.11,
    "source": "yahoo_finance",
    "fetched_at": "2026-04-12T03:25:18.444601+00:00"
  },
  {
    "key": "dowjones",
    "name": "Dow Jones Industrial Average",
    "symbol": "^DJI",
    "price": 47916.57,
    "change_percent": -0.56,
    "source": "yahoo_finance",
    "fetched_at": "2026-04-12T03:25:18.444601+00:00"
  },
  {
    "key": "a_share_sse",
    "name": "上证指数",
    "symbol": "000001",
    "price": 3986.22,
    "change_percent": 0.51,
    "source": "eastmoney",
    "fetched_at": "2026-04-12T03:25:18.444601+00:00"
  },
  {
    "key": "nikkei225",
    "name": "Nikkei 225",
    "symbol": "^N225",
    "price": 56924.11,
    "change_percent": 1.84,
    "source": "yahoo_finance",
    "fetched_at": "2026-04-12T03:25:18.444601+00:00"
  },
  {
    "key": "hangseng",
    "name": "Hang Seng Index",
    "symbol": "^HSI",
    "price": 25893.54,
    "change_percent": 0.55,
    "source": "yahoo_finance",
    "fetched_at": "2026-04-12T03:25:18.444601+00:00"
  }
]