[
  {
    "id": 1,
    "dedupe_key": "urn:oid:2.49.0.1.840.0.671a06eb43e5c97ad2bff18dc0fcb0932c30a2ba.001.1",
    "source_primary": "WMO",
    "title": "Extreme Wind Warning issued April 14 at 11:54PM ChST until April 15 at 3:00AM ChST by NWS Tiyan GU",
    "summary": "Saipan, MP; Tinian, MP",
    "severity_level": "extreme",
    "color_level": "extreme",
    "event_type": "weather",
    "location_text": "Saipan, MP; Tinian, MP",
    "issued_at": "2026-04-14T14:02:00+00:00",
    "effective_at": "2026-04-14T13:54:00+00:00",
    "expires_at": "2026-04-14T17:00:00+00:00",
    "source_url": "https://severeweather.wmo.int/list.html",
    "detail_url": "https://severeweather.wmo.int/list.html",
    "payload": {
      "id": "urn:oid:2.49.0.1.840.0.671a06eb43e5c97ad2bff18dc0fcb0932c30a2ba.001.1",
      "event": "Extreme Wind Warning",
      "headline": "Extreme Wind Warning issued April 14 at 11:54PM ChST until April 15 at 3:00AM ChST by NWS Tiyan GU",
      "sent": "2026-04-14 14:02:00",
      "expires": "2026-04-14 17:00:00",
      "areaDesc": "Saipan, MP; Tinian, MP",
      "mid": "093",
      "ra": "4",
      "s": 4,
      "u": 4,
      "c": 4,
      "capURL": "us-noaa-nws-en/2026/04/14/14/02/00-bcfa7ffe3092014476a8ae0236d8d766.xml",
      "effective": "2026-04-14 13:54:00",
      "cap_path": "us-noaa-nws-en/2026/04/14/14/02/00-bcfa7ffe3092014476a8ae0236d8d766.xml",
      "source_page": "https://severeweather.wmo.int/list.html",
      "last_updated": "2026-04-14 15:19:15"
    },
    "fetched_at": "2026-04-14T15:20:27.204699+00:00",
    "published_at": "2026-04-14T14:02:00+00:00",
    "updated_at": "2026-04-14T15:20:27.204699+00:00",
    "region_text": "Saipan, MP; Tinian, MP",
    "link_url": "https://severeweather.wmo.int/list.html"
  },
  {
    "id": 2,
    "dedupe_key": "IN-1776171562386008_8",
    "source_primary": "WMO",
    "title": "Heat Wave is Likely to occur over 23 Mandals. Please follow SDMA guidelines.",
    "summary": "23 Mandals",
    "severity_level": "extreme",
    "color_level": "extreme",
    "event_type": "weather",
    "location_text": "23 Mandals",
    "issued_at": "2026-04-14T13:29:22+00:00",
    "effective_at": "2026-04-14T13:30:00+00:00",
    "expires_at": "2026-04-14T21:30:00+00:00",
    "source_url": "https://severeweather.wmo.int/list.html",
    "detail_url": "https://severeweather.wmo.int/list.html",
    "payload": {
      "id": "IN-1776171562386008_8",
      "event": "Heat Wave",
      "headline": "Heat Wave is Likely to occur over 23 Mandals. Please follow SDMA guidelines.",
      "sent": "2026-04-14 13:29:22",
      "expires": "2026-04-14 21:30:00",
      "areaDesc": "23 Mandals",
      "mid": "066",
      "ra": "2",
      "s": 4,
      "u": 4,
      "c": 2,
      "url": "in-ndma-xx/2026/04/14/13/29/22-e0765368269c27b135a2c7f9a1ddcea1.xml",
      "effective": "2026-04-14 13:30:00",
      "cap_path": "in-ndma-xx/2026/04/14/13/29/22-e0765368269c27b135a2c7f9a1ddcea1.xml",
      "source_page": "https://severeweather.wmo.int/list.html",
      "last_updated": "2026-04-14 15:19:15"
    },
    "fetched_at": "2026-04-14T15:20:27.204699+00:00",
    "published_at": "2026-04-14T13:29:22+00:00",
    "updated_at": "2026-04-14T15:20:27.204699+00:00",
    "region_text": "23 Mandals",
    "link_url": "https://severeweather.wmo.int/list.html"
  },
  {
    "id": 3,
    "dedupe_key": "IN-1776171173054008_8",
    "source_primary": "WMO",
    "title": "Heat Wave is Likely to occur over 23 Mandals. Please follow SDMA guidelines.",
    "summary": "23 Mandals",
    "severity_level": "extreme",
    "color_level": "extreme",
    "event_type": "weather",
    "location_text": "23 Mandals",
    "issued_at": "2026-04-14T13:22:53+00:00",
    "effective_at": "2026-04-14T13:20:00+00:00",
    "expires_at": "2026-04-14T21:20:00+00:00",
    "source_url": "https://severeweather.wmo.int/list.html",
    "detail_url": "https://severeweather.wmo.int/list.html",
    "payload": {
      "id": "IN-1776171173054008_8",
      "event": "Heat Wave",
      "headline": "Heat Wave is Likely to occur over 23 Mandals. Please follow SDMA guidelines.",
      "sent": "2026-04-14 13:22:53",
      "expires": "2026-04-14 21:20:00",
      "areaDesc": "23 Mandals",
      "mid": "066",
      "ra": "2",
      "s": 4,
      "u": 4,
      "c": 2,
      "url": "in-ndma-xx/2026/04/14/13/22/53-f79141fa91355e6ca83fdd57737ae962.xml",
      "effective": "2026-04-14 13:20:00",
      "cap_path": "in-ndma-xx/2026/04/14/13/22/53-f79141fa91355e6ca83fdd57737ae962.xml",
      "source_page": "https://severeweather.wmo.int/list.html",
      "last_updated": "2026-04-14 15:19:15"
    },
    "fetched_at": "2026-04-14T15:20:27.204699+00:00",
    "published_at": "2026-04-14T13:22:53+00:00",
    "updated_at": "2026-04-14T15:20:27.204699+00:00",
    "region_text": "23 Mandals",
    "link_url": "https://severeweather.wmo.int/list.html"
  },
  {
    "id": 4,
    "dedupe_key": "urn:oid:2.49.0.1.840.0.24150f267560494cedbe327aa7084b1bc6dc785f.001.1",
    "source_primary": "WMO",
    "title": "Typhoon Warning issued April 14 at 10:20PM ChST by NWS Tiyan GU",
    "summary": "Rota Coastal Waters; Tinian Coastal Waters; Saipan Coastal Waters",
    "severity_level": "extreme",
    "color_level": "extreme",
    "event_type": "weather",
    "location_text": "Rota Coastal Waters; Tinian Coastal Waters; Saipan Coastal Waters",
    "issued_at": "2026-04-14T12:20:00+00:00",
    "effective_at": "2026-04-14T12:20:00+00:00",
    "expires_at": "2026-04-15T03:30:00+00:00",
    "source_url": "https://severeweather.wmo.int/list.html",
    "detail_url": "https://severeweather.wmo.int/list.html",
    "payload": {
      "id": "urn:oid:2.49.0.1.840.0.24150f267560494cedbe327aa7084b1bc6dc785f.001.1",
      "event": "Typhoon Warning",
      "headline": "Typhoon Warning issued April 14 at 10:20PM ChST by NWS Tiyan GU",
      "sent": "2026-04-14 12:20:00",
      "expires": "2026-04-15 03:30:00",
      "areaDesc": "Rota Coastal Waters; Tinian Coastal Waters; Saipan Coastal Waters",
      "mid": "093",
      "ra": "4",
      "s": 4,
      "u": 4,
      "c": 3,
      "capURL": "us-noaa-nws-en-marine/2026/04/14/12/20/00-7fca40ea9cb25a551c9574e449c0181a.xml",
      "effective": "2026-04-14 12:20:00",
      "cap_path": "us-noaa-nws-en-marine/2026/04/14/12/20/00-7fca40ea9cb25a551c9574e449c0181a.xml",
      "source_page": "https://severeweather.wmo.int/list.html",
      "last_updated": "2026-04-14 15:19:15"
    },
    "fetched_at": "2026-04-14T15:20:27.204699+00:00",
    "published_at": "2026-04-14T12:20:00+00:00",
    "updated_at": "2026-04-14T15:20:27.204699+00:00",
    "region_text": "Rota Coastal Waters; Tinian Coastal Waters; Saipan Coastal Waters",
    "link_url": "https://severeweather.wmo.int/list.html"
  },
  {
    "id": 5,
    "dedupe_key": "urn:oid:2.49.0.1.840.0.8b8d1d20e6b1c113f5b07da628f60a7182415fba.002.1",
    "source_primary": "WMO",
    "title": "Typhoon Warning issued April 14 at 10:02PM ChST by NWS Tiyan GU",
    "summary": "Rota; Tinian; Saipan",
    "severity_level": "extreme",
    "color_level": "extreme",
    "event_type": "weather",
    "location_text": "Rota; Tinian; Saipan",
    "issued_at": "2026-04-14T12:02:00+00:00",
    "effective_at": "2026-04-14T12:02:00+00:00",
    "expires_at": "2026-04-14T20:45:00+00:00",
    "source_url": "https://severeweather.wmo.int/list.html",
    "detail_url": "https://severeweather.wmo.int/list.html",
    "payload": {
      "id": "urn:oid:2.49.0.1.840.0.8b8d1d20e6b1c113f5b07da628f60a7182415fba.002.1",
      "event": "Typhoon Warning",
      "headline": "Typhoon Warning issued April 14 at 10:02PM ChST by NWS Tiyan GU",
      "sent": "2026-04-14 12:02:00",
      "expires": "2026-04-14 20:45:00",
      "areaDesc": "Rota; Tinian; Saipan",
      "mid": "093",
      "ra": "4",
      "s": 4,
      "u": 4,
      "c": 3,
      "capURL": "us-noaa-nws-en/2026/04/14/12/02/00-691350576455023cfd0f77fdf757f88e.xml",
      "effective": "2026-04-14 12:02:00",
      "cap_path": "us-noaa-nws-en/2026/04/14/12/02/00-691350576455023cfd0f77fdf757f88e.xml",
      "source_page": "https://severeweather.wmo.int/list.html",
      "last_updated": "2026-04-14 15:19:15"
    },
    "fetched_at": "2026-04-14T15:20:27.204699+00:00",
    "published_at": "2026-04-14T12:02:00+00:00",
    "updated_at": "2026-04-14T15:20:27.204699+00:00",
    "region_text": "Rota; Tinian; Saipan",
    "link_url": "https://severeweather.wmo.int/list.html"
  },
  {
    "id": 6,
    "dedupe_key": "2.49.0.0.398.0-20260414-111701-0417620-00-EN",
    "source_primary": "WMO",
    "title": "Wind",
    "summary": "Beyneu district (Mangystau Region)",
    "severity_level": "extreme",
    "color_level": "extreme",
    "event_type": "weather",
    "location_text": "Beyneu district (Mangystau Region)",
    "issued_at": "2026-04-14T11:17:01+00:00",
    "effective_at": "2026-04-14T11:17:01+00:00",
    "expires_at": "2026-04-15T15:00:00+00:00",
    "source_url": "https://severeweather.wmo.int/list.html",
    "detail_url": "https://severeweather.wmo.int/list.html",
    "payload": {
      "id": "2.49.0.0.398.0-20260414-111701-0417620-00-EN",
      "event": "Wind",
      "headline": "Wind",
      "sent": "2026-04-14 11:17:01",
      "expires": "2026-04-15 15:00:00",
      "areaDesc": "Beyneu district (Mangystau Region)",
      "mid": "070",
      "ra": "2",
      "s": 4,
      "u": 2,
      "c": 3,
      "capURL": "kz-kazhydromet-en/2026/04/14/11/17/01-f3940d0d0f7f3982ea9a0a1de7539dae.xml",
      "effective": "",
      "cap_path": "kz-kazhydromet-en/2026/04/14/11/17/01-f3940d0d0f7f3982ea9a0a1de7539dae.xml",
      "source_page": "https://severeweather.wmo.int/list.html",
      "last_updated": "2026-04-14 15:19:15"
    },
    "fetched_at": "2026-04-14T15:20:27.204699+00:00",
    "published_at": "2026-04-14T11:17:01+00:00",
    "updated_at": "2026-04-14T15:20:27.204699+00:00",
    "region_text": "Beyneu district (Mangystau Region)",
    "link_url": "https://severeweather.wmo.int/list.html"
  },
  {
    "id": 7,
    "dedupe_key": "2.49.0.1.578.1.260414102946.460774",
    "source_primary": "WMO",
    "title": "High avalanche danger for region Svalbard vest 2026-04-15",
    "summary": "Svalbard vest",
    "severity_level": "extreme",
    "color_level": "extreme",
    "event_type": "weather",
    "location_text": "Svalbard vest",
    "issued_at": "2026-04-14T08:29:46+00:00",
    "effective_at": "2026-04-14T22:00:00+00:00",
    "expires_at": "2026-04-15T21:59:59+00:00",
    "source_url": "https://severeweather.wmo.int/list.html",
    "detail_url": "https://severeweather.wmo.int/list.html",
    "payload": {
      "id": "2.49.0.1.578.1.260414102946.460774",
      "event": "avalanches",
      "headline": "High avalanche danger for region Svalbard vest 2026-04-15",
      "sent": "2026-04-14 08:29:46",
      "expires": "2026-04-15 21:59:59",
      "areaDesc": "Svalbard vest",
      "mid": "008",
      "ra": "6",
      "s": 4,
      "u": 2,
      "c": 3,
      "url": "no-nve-xx/2026/04/14/08/29/46-8fbac8ed39f5b3b361c10f7141c3d891.xml",
      "effective": "2026-04-14 22:00:00",
      "cap_path": "no-nve-xx/2026/04/14/08/29/46-8fbac8ed39f5b3b361c10f7141c3d891.xml",
      "source_page": "https://severeweather.wmo.int/list.html",
      "last_updated": "2026-04-14 15:19:15"
    },
    "fetched_at": "2026-04-14T15:20:27.204699+00:00",
    "published_at": "2026-04-14T08:29:46+00:00",
    "updated_at": "2026-04-14T15:20:27.204699+00:00",
    "region_text": "Svalbard vest",
    "link_url": "https://severeweather.wmo.int/list.html"
  }
]